AUTHORS.txt
CHANGELOG
LICENSE.txt
MANIFEST.in
Makefile
README.rst
setup.cfg
setup.py
gfbi_core/__init__.py
gfbi_core/editable_git_model.py
gfbi_core/git_filter_branch_process.py
gfbi_core/git_model.py
gfbi_core/git_rebase_process.py
gfbi_core/non_continuous_timelapse.py
gfbi_core/util.py
gfbi_core/validation.py
gfbi_core.egg-info/PKG-INFO
gfbi_core.egg-info/SOURCES.txt
gfbi_core.egg-info/dependency_links.txt
gfbi_core.egg-info/requires.txt
gfbi_core.egg-info/top_level.txt