Metadata-Version: 1.0
Name: gfbi-core
Version: 0.3b1
Summary: Core files for interactive git filter branch.
Home-page: https://github.com/mike-perdide/qfbi_core
Author: Julien Miotte
Author-email: mike.perdide@gmail.com
License: GPLv3
Keywords: git,change dates,rewrite history
Platform: UNKNOWN
